quisp/__init__.py
quisp/_frontend.py
quisp/_version.py
quisp/widget.py
quisp/labextension/package.json
quisp/labextension/static/367.89662278e354c33feaf2.js
quisp/labextension/static/480.6a30837618657a2a61b2.js
quisp/labextension/static/568.492546783f96764ac5ea.js
quisp/labextension/static/remoteEntry.a3d1a240c2e5e78efb5b.js
quisp/labextension/static/style.js
quisp/labextension/static/third-party-licenses.json
quisp/nbextension/extension.js
quisp/nbextension/index.js
quisp/nbextension/index.js.map
quisp/planner/__init__.py
quisp/planner/channel.py
quisp/planner/config.py
quisp/planner/network.py
quisp/planner/qnode.py
quisp/planner/types.py
quisp/tests/__init__.py
quisp/tests/conftest.py
quisp/tests/test_nbextension_path.py
quisp/tests/test_network.py
quisp/worker/__init__.py
quisp/worker/native.py
quisp-0.3.0.data/data/share/jupyter/labextensions/quisp/package.json
quisp-0.3.0.data/data/share/jupyter/labextensions/quisp/static/367.89662278e354c33feaf2.js
quisp-0.3.0.data/data/share/jupyter/labextensions/quisp/static/480.6a30837618657a2a61b2.js
quisp-0.3.0.data/data/share/jupyter/labextensions/quisp/static/568.492546783f96764ac5ea.js
quisp-0.3.0.data/data/share/jupyter/labextensions/quisp/static/remoteEntry.a3d1a240c2e5e78efb5b.js
quisp-0.3.0.data/data/share/jupyter/labextensions/quisp/static/style.js
quisp-0.3.0.data/data/share/jupyter/labextensions/quisp/static/third-party-licenses.json
quisp-0.3.0.data/data/share/jupyter/nbextensions/quisp/extension.js
quisp-0.3.0.data/data/share/jupyter/nbextensions/quisp/index.js
quisp-0.3.0.data/data/share/jupyter/nbextensions/quisp/index.js.map
quisp-0.3.0.data/data/etc/jupyter/nbconfig/notebook.d/quisp.json
quisp-0.3.0.data/data/share/jupyter/labextensions/quisp/install.json
quisp-0.3.0.dist-info/METADATA
quisp-0.3.0.dist-info/WHEEL
quisp-0.3.0.dist-info/licenses/LICENSE.txt
quisp-0.3.0.dist-info/RECORD
